unicorner_face_tracker/__init__.py
unicorner_face_tracker/face_tracker.py
unicorner_face_tracker-0.1.0.dist-info/licenses/LICENSE
unicorner_face_tracker-0.1.0.dist-info/METADATA
unicorner_face_tracker-0.1.0.dist-info/WHEEL
unicorner_face_tracker-0.1.0.dist-info/top_level.txt
unicorner_face_tracker-0.1.0.dist-info/RECORD
