Metadata-Version: 2.4
Name: unicorner-face-tracker
Version: 0.1.0
Summary: Simple IoU-based face tracker with persistent IDs
Author-email: Ruslan Kovalev <kovalyovruslan@gamil.com>
License: MIT
Requires-Python: >=3.7
License-File: LICENSE
Requires-Dist: numpy
Dynamic: license-file
